{
  "id": "vanguard_heavy_support_auto",
  "name": "Heavy Support Auto",
  "cost": 50,
  "icon": "assets/icons/units/vanguard/vanguard_heavy_support_auto.png",
  "health": 10,
  "speed": {
    "road": 70,
    "offRoad": 50,
    "rotation": 8
  },
  "armor": {
    "front": 20,
    "side": 20,
    "rear": 20,
    "top": 20
  },
  "fuel": null,
  "autonomy": null,
  "optics": "Very Good",
  "stealth": "Poor",
  "forwardDeploy": 0,
  "weapons": [
    {
      "weaponId": "vanguard_heavy_auto_cannon",
      "count": 4,
      "maxAmmo": 10,
      "turretMounted": false
    },
    {
      "weaponId": "vanguard_kinetic_rifle",
      "count": 1,
      "maxAmmo": 20,
      "turretMounted": false
    }
  ],
  "category": "INF",
  "tags": [],
  "isCommander": false,
  "commanderAuraRadius": 0,
  "transportCapacity": 0,
  "canBeTransported": true,
  "transportSize": 1,
  "veterancyBonus": 0.1
}
